HISTORY.txt
README.txt
setup.cfg
setup.py
Products/__init__.py
Products.Zope_Hotfix_20110622.egg-info/PKG-INFO
Products.Zope_Hotfix_20110622.egg-info/SOURCES.txt
Products.Zope_Hotfix_20110622.egg-info/dependency_links.txt
Products.Zope_Hotfix_20110622.egg-info/namespace_packages.txt
Products.Zope_Hotfix_20110622.egg-info/not-zip-safe
Products.Zope_Hotfix_20110622.egg-info/requires.txt
Products.Zope_Hotfix_20110622.egg-info/top_level.txt
Products/Zope_Hotfix_20110622/__init__.py
Products/Zope_Hotfix_20110622/patch.py