Metadata-Version: 1.0
Name: Products.Zope-Hotfix-20110622
Version: 1.0
Summary: UNKNOWN
Home-page: http://plone.org/products/plone-hotfix/releases/20110622
Author: Zope Foundation and Contributors
Author-email: zope-dev@zope.org
License: ZPL 2.1
Keywords: security hotfix patch
Platform: UNKNOWN
Classifier: Programming Language :: Python
Classifier: Framework :: Zope2
Classifier: License :: OSI Approved :: Zope Public License
